locify/__init__.py
locify/cli.py
locify/indexing/direct_ref/extractor.py
locify/indexing/direct_ref/strategy.py
locify/indexing/full_map/README.md
locify/indexing/full_map/strategy.py
locify/indexing/prompts.py
locify/indexing/repo_map/README.md
locify/indexing/repo_map/strategy.py
locify/tree_sitter/parser.py
locify/tree_sitter/queries/README.md
locify/tree_sitter/queries/tree-sitter-c-tags.scm
locify/tree_sitter/queries/tree-sitter-c_sharp-tags.scm
locify/tree_sitter/queries/tree-sitter-cpp-tags.scm
locify/tree_sitter/queries/tree-sitter-elisp-tags.scm
locify/tree_sitter/queries/tree-sitter-elixir-tags.scm
locify/tree_sitter/queries/tree-sitter-elm-tags.scm
locify/tree_sitter/queries/tree-sitter-go-tags.scm
locify/tree_sitter/queries/tree-sitter-java-tags.scm
locify/tree_sitter/queries/tree-sitter-javascript-tags.scm
locify/tree_sitter/queries/tree-sitter-ocaml-tags.scm
locify/tree_sitter/queries/tree-sitter-php-tags.scm
locify/tree_sitter/queries/tree-sitter-python-tags.scm
locify/tree_sitter/queries/tree-sitter-ql-tags.scm
locify/tree_sitter/queries/tree-sitter-ruby-tags.scm
locify/tree_sitter/queries/tree-sitter-rust-tags.scm
locify/tree_sitter/queries/tree-sitter-typescript-tags.scm
locify/utils/__init__.py
locify/utils/chat_history.py
locify/utils/file.py
locify/utils/llm.py
locify/utils/path.py
locify-0.0.9.dist-info/LICENSE
locify-0.0.9.dist-info/METADATA
locify-0.0.9.dist-info/WHEEL
locify-0.0.9.dist-info/RECORD
