Metadata-Version: 2.1
Name: locify
Version: 0.0.9
Summary: A library for LLM-based agents to navigate large codebases efficiently.
License: MIT
Author: Hoang Tran
Author-email: descience.thh10@gmail.com
Requires-Python: >=3.12,<4.0
Classifier: License :: OSI Approved :: MIT License
Classifier: Programming Language :: Python :: 3
Classifier: Programming Language :: Python :: 3.12
Classifier: Programming Language :: Python :: 3.13
Requires-Dist: diskcache (>=5.6.3,<6.0.0)
Requires-Dist: fire
Requires-Dist: gitpython
Requires-Dist: grep-ast (==0.3.3)
Requires-Dist: litellm
Requires-Dist: networkx
Requires-Dist: numpy
Requires-Dist: pandas
Requires-Dist: python-dotenv (>=1.0.1,<2.0.0)
Requires-Dist: pyvis (>=0.3.2,<0.4.0)
Requires-Dist: scipy
Requires-Dist: tree-sitter (==0.21.3)
